setup.py
mongodb_helper/util.py
zawn_helper/__init__.py
zawn_helper/db_helper.py
zawn_helper/id_helper.py
zawn_helper/search_helper.py
zawn_helper/token_helper.py
zawn_state_helper/__init__.py
zawn_state_helper/base.py
zawn_state_helper/general_state.py
zawn_utils.egg-info/PKG-INFO
zawn_utils.egg-info/SOURCES.txt
zawn_utils.egg-info/dependency_links.txt
zawn_utils.egg-info/requires.txt
zawn_utils.egg-info/top_level.txt
zawn_workflow/__init__.py
zawn_workflow/context/__init__.py
zawn_workflow/context/base.py
zawn_workflow/context/context.py
zawn_workflow/context/identity.py
zawn_workflow/context/repository.py
zawn_workflow/context/runtime.py
zawn_workflow/context/searcher.py
zawn_workflow/data/__init__.py
zawn_workflow/data/exception.py
zawn_workflow/data/factory.py
zawn_workflow/data/state.py
zawn_workflow/role/__init__.py
zawn_workflow/role/designer.py
zawn_workflow/role/handler.py
zawn_workflow/role/initiator.py
zawn_workflow/test/__init__.py
zawn_workflow/test/test.py
zawn_workflow/test/test_identity.py
zawn_workflow/test/test_repository.py
zawn_workflow/test/test_runtime.py
zawn_workflow/test/test_searcher.py