Metadata-Version: 2.1
Name: zawn-utils
Version: 0.0.12
Summary: zawn's private utils.
Home-page: https://github.com/zawn/utils
Author: zawn
Author-email: zawn@qq.com
License: MIT Licence
Keywords: zawn,utils
Platform: any
